<?xml version="1.0" encoding="UTF-8"?>
<window>
	<!-- startup -->
	<onload>Skin.Reset(HideSettings)</onload>
	<onload>ReplaceWindow($INFO[System.StartupWindow])</onload>
	<!--Default Skin Settings-->
	<onload condition="String.IsEmpty(Skin.String(Theme))">Skin.SetString(Theme,Dark)</onload>

	<onload condition="String.IsEmpty(Skin.String(ListView_Display_Movies))">Skin.SetString(ListView_Display_Movies,Background)</onload>
	<onload condition="String.IsEmpty(Skin.String(ListView_Display_Sets))">Skin.SetString(ListView_Display_Sets,Background)</onload>
	<onload condition="String.IsEmpty(Skin.String(ListView_Display_TVShows))">Skin.SetString(ListView_Display_TVShows,Background)</onload>
	<onload condition="String.IsEmpty(Skin.String(ListView_Display_Seasons))">Skin.SetString(ListView_Display_Seasons,Background)</onload>
	<onload condition="String.IsEmpty(Skin.String(ListView_Display_Episodes))">Skin.SetString(ListView_Display_Episodes,Background)</onload>
	<onload condition="String.IsEmpty(Skin.String(ListView_Display_Artists))">Skin.SetString(ListView_Display_Artists,Background)</onload>
	<onload condition="String.IsEmpty(Skin.String(ListView_Display_Albums))">Skin.SetString(ListView_Display_Albums,Background)</onload>
	<onload condition="String.IsEmpty(Skin.String(ListView_Display_Songs))">Skin.SetString(ListView_Display_Songs,Background)</onload>
	<onload condition="String.IsEmpty(Skin.String(ListView_Details_Movies))">Skin.SetString(ListView_Details_Movies,TitleAndInfo)</onload>
	<onload condition="String.IsEmpty(Skin.String(ListView_Details_Sets))">Skin.SetString(ListView_Details_Sets,TitleAndInfo)</onload>
	<onload condition="String.IsEmpty(Skin.String(ListView_Details_TVShows))">Skin.SetString(ListView_Details_TVShows,TitleAndInfo)</onload>
	<onload condition="String.IsEmpty(Skin.String(ListView_Details_Seasons))">Skin.SetString(ListView_Details_Seasons,TitleAndInfo)</onload>
	<onload condition="String.IsEmpty(Skin.String(ListView_Details_Episodes))">Skin.SetString(ListView_Details_Episodes,TitleAndInfo)</onload>
	<onload condition="String.IsEmpty(Skin.String(ListView_Details_Artists))">Skin.SetString(ListView_Details_Artists,TitleAndInfo)</onload>
	<onload condition="String.IsEmpty(Skin.String(ListView_Details_Albums))">Skin.SetString(ListView_Details_Albums,TitleAndInfo)</onload>
	<onload condition="String.IsEmpty(Skin.String(ListView_Details_Songs))">Skin.SetString(ListView_Details_Songs,TitleAndInfo)</onload>
	<onload condition="String.IsEmpty(Skin.String(ListView_Flags_Movies))">Skin.SetString(ListView_Flags_Movies,All)</onload>
	<onload condition="String.IsEmpty(Skin.String(ListView_Flags_Sets))">Skin.SetString(ListView_Flags_Sets,All)</onload>
	<onload condition="String.IsEmpty(Skin.String(ListView_Flags_TVShows))">Skin.SetString(ListView_Flags_TVShows,All)</onload>
	<onload condition="String.IsEmpty(Skin.String(ListView_Flags_Seasons))">Skin.SetString(ListView_Flags_Seasons,All)</onload>
	<onload condition="String.IsEmpty(Skin.String(ListView_Flags_Episodes))">Skin.SetString(ListView_Flags_Episodes,All)</onload>

	<onload condition="String.IsEmpty(Skin.String(BillboardView_Details_Movies))">Skin.SetString(BillboardView_Details_Movies,All)</onload>
	<onload condition="String.IsEmpty(Skin.String(BillboardView_Details_Sets))">Skin.SetString(BillboardView_Details_Sets,All)</onload>
	<onload condition="String.IsEmpty(Skin.String(BillboardView_Details_TVShows))">Skin.SetString(BillboardView_Details_TVShows,All)</onload>
	<onload condition="String.IsEmpty(Skin.String(BillboardView_Details_Seasons))">Skin.SetString(BillboardView_Details_Seasons,TitleAndInfo)</onload>
	<onload condition="String.IsEmpty(Skin.String(BillboardView_Details_Episodes))">Skin.SetString(BillboardView_Details_Episodes,All)</onload>
	<onload condition="String.IsEmpty(Skin.String(BillboardView_Details_Artists))">Skin.SetString(BillboardView_Details_Artists,Title)</onload>
	<onload condition="String.IsEmpty(Skin.String(BillboardView_Logo_Movies))">Skin.SetString(BillboardView_Logo_Movies,Off)</onload>
	<onload condition="String.IsEmpty(Skin.String(BillboardView_Logo_Sets))">Skin.SetString(BillboardView_Logo_Sets,Off)</onload>
	<onload condition="String.IsEmpty(Skin.String(BillboardView_Logo_TVShows))">Skin.SetString(BillboardView_Logo_TVShows,Off)</onload>
	<onload condition="String.IsEmpty(Skin.String(BillboardView_Logo_Artists))">Skin.SetString(BillboardView_Logo_Artists,Off)</onload>
	<onload condition="String.IsEmpty(Skin.String(BillboardView_Flags_Movies))">Skin.SetString(BillboardView_Flags_Movies,All)</onload>
	<onload condition="String.IsEmpty(Skin.String(BillboardView_Flags_Sets))">Skin.SetString(BillboardView_Flags_Sets,All)</onload>
	<onload condition="String.IsEmpty(Skin.String(BillboardView_Flags_TVShows))">Skin.SetString(BillboardView_Flags_TVShows,All)</onload>
	<onload condition="String.IsEmpty(Skin.String(BillboardView_Flags_Seasons))">Skin.SetString(BillboardView_Flags_Seasons,All)</onload>
	<onload condition="String.IsEmpty(Skin.String(BillboardView_Flags_Episodes))">Skin.SetString(BillboardView_Flags_Episodes,All)</onload>

	<onload condition="String.IsEmpty(Skin.String(ShowcaseView_Display_Movies))">Skin.SetString(ShowcaseView_Display_Movies,Posters)</onload>
	<onload condition="String.IsEmpty(Skin.String(ShowcaseView_Display_Sets))">Skin.SetString(ShowcaseView_Display_Sets,Posters)</onload>
	<onload condition="String.IsEmpty(Skin.String(ShowcaseView_Display_TVShows))">Skin.SetString(ShowcaseView_Display_TVShows,Posters)</onload>
	<onload condition="String.IsEmpty(Skin.String(ShowcaseView_Display_Seasons))">Skin.SetString(ShowcaseView_Display_Seasons,Posters)</onload>
	<onload condition="String.IsEmpty(Skin.String(ShowcaseView_Details_Movies))">Skin.SetString(ShowcaseView_Details_Movies,All)</onload>
	<onload condition="String.IsEmpty(Skin.String(ShowcaseView_Details_Sets))">Skin.SetString(ShowcaseView_Details_Sets,All)</onload>
	<onload condition="String.IsEmpty(Skin.String(ShowcaseView_Details_TVShows))">Skin.SetString(ShowcaseView_Details_TVShows,All)</onload>
	<onload condition="String.IsEmpty(Skin.String(ShowcaseView_Details_Seasons))">Skin.SetString(ShowcaseView_Details_Seasons,TitleAndInfo)</onload>
	<onload condition="String.IsEmpty(Skin.String(ShowcaseView_Details_Episodes))">Skin.SetString(ShowcaseView_Details_Episodes,All)</onload>
	<onload condition="String.IsEmpty(Skin.String(ShowcaseView_Details_Artists))">Skin.SetString(ShowcaseView_Details_Artists,TitleAndInfo)</onload>
	<onload condition="String.IsEmpty(Skin.String(ShowcaseView_Details_Albums))">Skin.SetString(ShowcaseView_Details_Albums,TitleAndInfo)</onload>
	<onload condition="String.IsEmpty(Skin.String(ShowcaseView_Logo_Movies))">Skin.SetString(ShowcaseView_Logo_Movies,Off)</onload>
	<onload condition="String.IsEmpty(Skin.String(ShowcaseView_Logo_Sets))">Skin.SetString(ShowcaseView_Logo_Sets,Off)</onload>
	<onload condition="String.IsEmpty(Skin.String(ShowcaseView_Logo_TVShows))">Skin.SetString(ShowcaseView_Logo_TVShows,Off)</onload>
	<onload condition="String.IsEmpty(Skin.String(ShowcaseView_Logo_Artists))">Skin.SetString(ShowcaseView_Logo_Artists,Off)</onload>
	<onload condition="String.IsEmpty(Skin.String(ShowcaseView_Flags_Movies))">Skin.SetString(ShowcaseView_Flags_Movies,All)</onload>
	<onload condition="String.IsEmpty(Skin.String(ShowcaseView_Flags_Sets))">Skin.SetString(ShowcaseView_Flags_Sets,All)</onload>
	<onload condition="String.IsEmpty(Skin.String(ShowcaseView_Flags_TVShows))">Skin.SetString(ShowcaseView_Flags_TVShows,All)</onload>
	<onload condition="String.IsEmpty(Skin.String(ShowcaseView_Flags_Seasons))">Skin.SetString(ShowcaseView_Flags_Seasons,All)</onload>
	<onload condition="String.IsEmpty(Skin.String(ShowcaseView_Flags_Episodes))">Skin.SetString(ShowcaseView_Flags_Episodes,All)</onload>

	<onload condition="String.IsEmpty(Skin.String(StripView_Display_Movies))">Skin.SetString(StripView_Display_Movies,Posters)</onload>
	<onload condition="String.IsEmpty(Skin.String(StripView_Display_Sets))">Skin.SetString(StripView_Display_Sets,Posters)</onload>
	<onload condition="String.IsEmpty(Skin.String(StripView_Display_TVShows))">Skin.SetString(StripView_Display_TVShows,Posters)</onload>
	<onload condition="String.IsEmpty(Skin.String(StripView_Display_Seasons))">Skin.SetString(StripView_Display_Seasons,Posters)</onload>
	<onload condition="String.IsEmpty(Skin.String(StripView_Display_Artists))">Skin.SetString(StripView_Display_Artists,Fanart)</onload>
	<onload condition="String.IsEmpty(Skin.String(StripView_Display_Albums))">Skin.SetString(StripView_Display_Artists,Square)</onload>
	<onload condition="String.IsEmpty(Skin.String(StripView_Details_Movies))">Skin.SetString(StripView_Details_Movies,All)</onload>
	<onload condition="String.IsEmpty(Skin.String(StripView_Details_Sets))">Skin.SetString(StripView_Details_Sets,All)</onload>
	<onload condition="String.IsEmpty(Skin.String(StripView_Details_TVShows))">Skin.SetString(StripView_Details_TVShows,All)</onload>
	<onload condition="String.IsEmpty(Skin.String(StripView_Details_Seasons))">Skin.SetString(StripView_Details_Seasons,TitleAndInfo)</onload>
	<onload condition="String.IsEmpty(Skin.String(StripView_Details_Episodes))">Skin.SetString(StripView_Details_Episodes,All)</onload>
	<onload condition="String.IsEmpty(Skin.String(StripView_Details_Artists))">Skin.SetString(StripView_Details_Artists,TitleAndInfo)</onload>
	<onload condition="String.IsEmpty(Skin.String(StripView_Details_Albums))">Skin.SetString(StripView_Details_Albums,TitleAndInfo)</onload>
	<onload condition="String.IsEmpty(Skin.String(StripView_Logo_Movies))">Skin.SetString(StripView_Logo_Movies,Off)</onload>
	<onload condition="String.IsEmpty(Skin.String(StripView_Logo_Sets))">Skin.SetString(StripView_Logo_Sets,Off)</onload>
	<onload condition="String.IsEmpty(Skin.String(StripView_Logo_TVShows))">Skin.SetString(StripView_Logo_TVShows,Off)</onload>
	<onload condition="String.IsEmpty(Skin.String(StripView_Logo_Artists))">Skin.SetString(StripView_Logo_Artists,Off)</onload>
	<onload condition="String.IsEmpty(Skin.String(StripView_Flags_Movies))">Skin.SetString(StripView_Flags_Movies,All)</onload>
	<onload condition="String.IsEmpty(Skin.String(StripView_Flags_Sets))">Skin.SetString(StripView_Flags_Sets,All)</onload>
	<onload condition="String.IsEmpty(Skin.String(StripView_Flags_TVShows))">Skin.SetString(StripView_Flags_TVShows,All)</onload>
	<onload condition="String.IsEmpty(Skin.String(StripView_Flags_Seasons))">Skin.SetString(StripView_Flags_Seasons,All)</onload>
	<onload condition="String.IsEmpty(Skin.String(StripView_Flags_Episodes))">Skin.SetString(StripView_Flags_Episodes,All)</onload>

	<onload condition="String.IsEmpty(Skin.String(GridView_Display_Movies))">Skin.SetString(GridView_Display_Movies,Fanart)</onload>
	<onload condition="String.IsEmpty(Skin.String(GridView_Display_Sets))">Skin.SetString(GridView_Display_Sets,Fanart)</onload>
	<onload condition="String.IsEmpty(Skin.String(GridView_Display_TVShows))">Skin.SetString(GridView_Display_TVShows,Fanart)</onload>
	<onload condition="String.IsEmpty(Skin.String(GridView_Display_Seasons))">Skin.SetString(GridView_Display_Seasons,Fanart)</onload>
	<onload condition="String.IsEmpty(Skin.String(GridView_Display_Artists))">Skin.SetString(GridView_Display_Artists,Fanart)</onload>
	<onload condition="String.IsEmpty(Skin.String(GridView_Display_Albums))">Skin.SetString(GridView_Display_Artists,Fanart)</onload>
	<onload condition="String.IsEmpty(Skin.String(GridView_Details_Movies))">Skin.SetString(GridView_Details_Movies,Off)</onload>
	<onload condition="String.IsEmpty(Skin.String(GridView_Details_Sets))">Skin.SetString(GridView_Details_Sets,Off)</onload>
	<onload condition="String.IsEmpty(Skin.String(GridView_Details_TVShows))">Skin.SetString(GridView_Details_TVShows,Off)</onload>
	<onload condition="String.IsEmpty(Skin.String(GridView_Details_Seasons))">Skin.SetString(GridView_Details_Seasons,Off)</onload>
	<onload condition="String.IsEmpty(Skin.String(GridView_Details_Episodes))">Skin.SetString(GridView_Details_Episodes,Title)</onload>
	<onload condition="String.IsEmpty(Skin.String(GridView_Details_Artists))">Skin.SetString(GridView_Details_Artists,Off)</onload>
	<onload condition="String.IsEmpty(Skin.String(GridView_Details_Albums))">Skin.SetString(GridView_Details_Albums,Off)</onload>

	<onload>SetProperty(SkinInitStarted,1,Home)</onload>
</window>
