<?xml version="1.0" encoding="UTF-8"?>
<timers>
  <timer>
    <name>video_playback</name>
    <description>timer that starts whenever video has fullscreen playback</description>
    <start reset="true">Player.HasVideo</start>
    <stop>!Player.HasVideo</stop>
  </timer>
  <timer>
    <name>video_playback_label_interruptor</name>
    <description>timer started when videoosd or fullscreeninfo are loaded for the first time</description>
    <stop>!Player.HasVideo</stop>
  </timer>
  <timer>
    <name>music_visualisation</name>
    <description>timer that starts whenever music visualisation is showing</description>
  </timer>
  <timer>
    <name>gridview_fanart_topright</name>
    <start reset="true">Control.HasFocus(505) + Container.Position(2)</start>
    <stop>Control.HasFocus(505) + !Container.Position(2)</stop>
  </timer>
<!--  <timer>
    <name>trailer_autoplay_idle_timer</name>
    <start reset="true">System.IdleTime(3) + Window.IsVisible(videos) + !Player.HasMedia + !String.IsEmpty(ListItem.Trailer)</start>
    <onstart>PlayMedia($INFO[ListItem.Trailer],1,noresume)</onstart>
    <stop>Player.HasMedia</stop>
  </timer>-->
</timers>
